adafruit_circuitpython_onewire-2.0.12.dist-info/licenses/LICENSE
adafruit_onewire/__init__.py
adafruit_onewire/bus.py
adafruit_onewire/device.py
adafruit_circuitpython_onewire-2.0.12.dist-info/METADATA
adafruit_circuitpython_onewire-2.0.12.dist-info/WHEEL
adafruit_circuitpython_onewire-2.0.12.dist-info/top_level.txt
adafruit_circuitpython_onewire-2.0.12.dist-info/RECORD
