Metadata-Version: 2.4
Name: adafruit-circuitpython-onewire
Version: 2.0.12
Summary: CircuitPython OneWire helper library for 1-wire bus devices.
Author-email: Adafruit Industries <circuitpython@adafruit.com>
License: MIT
Project-URL: Homepage, https://github.com/adafruit/Adafruit_CircuitPython_OneWire
Keywords: adafruit,onewire,dallas,1-wire,breakout,hardware,micropython,circuitpython
Classifier: Intended Audience :: Developers
Classifier: Topic :: Software Development :: Libraries
Classifier: Topic :: Software Development :: Embedded Systems
Classifier: Topic :: System :: Hardware
Classifier: License :: OSI Approved :: MIT License
Classifier: Programming Language :: Python :: 3
License-File: LICENSE
Requires-Dist: Adafruit-Blinka
Requires-Dist: adafruit-circuitpython-busdevice
Requires-Dist: adafruit-circuitpython-typing
Provides-Extra: optional
Dynamic: license-file
